[{"updatedTime":"2024-09-05T21:21:41.367917100","description":"first","createdTime":"2024-09-05T21:21:41.366920","id":1,"status":"todo"},{"updatedTime":"2024-09-05T21:22:52.549388","description":"first","createdTime":"2024-09-05T21:22:52.549388","id":2,"status":"done"},{"updatedTime":"2024-09-05T21:23:00.401950400","description":"first","createdTime":"2024-09-05T21:23:00.401950400","id":4,"status":"todo"},{"updatedTime":"2024-09-05T21:23:01.544660200","description":"first","createdTime":"2024-09-05T21:23:01.544660200","id":5,"status":"todo"},{"updatedTime":"2024-09-05T21:23:39.200805","description":"check this","createdTime":"2024-09-05T21:23:39.200805","id":6,"status":"todo"}]